alkemy_workflow/VERSION
alkemy_workflow/__init__.py
alkemy_workflow/__main__.py
alkemy_workflow/cli.py
alkemy_workflow/clickup.py
alkemy_workflow/config.py
alkemy_workflow/exceptions.py
alkemy_workflow/git.py
alkemy_workflow/github.py
alkemy_workflow/planner.py
alkemy_workflow/utils.py
alkemy_workflow-0.3.3.dist-info/LICENSE
alkemy_workflow-0.3.3.dist-info/METADATA
alkemy_workflow-0.3.3.dist-info/WHEEL
alkemy_workflow-0.3.3.dist-info/entry_points.txt
alkemy_workflow-0.3.3.dist-info/top_level.txt
alkemy_workflow-0.3.3.dist-info/zip-safe
alkemy_workflow-0.3.3.dist-info/RECORD
